cli/__init__.py
cli/main.py
compose/__init__.py
compose/manage.py
gethue-0.26.dist-info/LICENSE.txt
gethue-0.26.dist-info/METADATA
gethue-0.26.dist-info/NOTICE.txt
gethue-0.26.dist-info/WHEEL
gethue-0.26.dist-info/entry_points.txt
gethue-0.26.dist-info/top_level.txt
gethue-0.26.dist-info/RECORD
