Metadata-Version: 2.1
Name: gethue
Version: 0.26
Summary: Open source SQL Query Assistant for Databases/Warehouses
Home-page: https://github.com/gethue/compose
Author: Gethue
Author-email: team@gethue.com
License: UNKNOWN
Platform: UNKNOWN
Classifier: Programming Language :: Python :: 3
Classifier: License :: OSI Approved :: Apache Software License
Classifier: Operating System :: OS Independent
Requires-Python: >=3.6
License-File: LICENSE.txt
License-File: NOTICE.txt
Requires-Dist: Django (~=3.1.7)
Requires-Dist: gunicorn (>=20.0.4)
Requires-Dist: drf-spectacular (>=0.13.2)
Requires-Dist: django-cors-headers (>=3.7.0)
Requires-Dist: djangorestframework (>=3.12.2)
Requires-Dist: djangorestframework-simplejwt (>=4.8.0)
Requires-Dist: opentracing (>=2.4.0)
Requires-Dist: requests (>=2.25.1)
Requires-Dist: SQLAlchemy (>=1.3.23)
Requires-Dist: typer (>=0.3.2)
Requires-Dist: whitenoise (>=5.3.0)
